odoo/addons/report_qweb_pdf_fixed_column/README.rst
odoo/addons/report_qweb_pdf_fixed_column/__init__.py
odoo/addons/report_qweb_pdf_fixed_column/__manifest__.py
odoo/addons/report_qweb_pdf_fixed_column/i18n/report_qweb_pdf_fixed_column.pot
odoo/addons/report_qweb_pdf_fixed_column/readme/CONTRIBUTORS.rst
odoo/addons/report_qweb_pdf_fixed_column/readme/DESCRIPTION.rst
odoo/addons/report_qweb_pdf_fixed_column/readme/USAGE.rst
odoo/addons/report_qweb_pdf_fixed_column/static/description/icon.png
odoo/addons/report_qweb_pdf_fixed_column/static/description/index.html
odoo/addons/report_qweb_pdf_fixed_column/static/src/css/report_qweb_pdf_fixed_column.scss
odoo/addons/report_qweb_pdf_fixed_column/views/assets.xml
odoo13_addon_report_qweb_pdf_fixed_column-13.0.1.0.1.dev3.dist-info/METADATA
odoo13_addon_report_qweb_pdf_fixed_column-13.0.1.0.1.dev3.dist-info/WHEEL
odoo13_addon_report_qweb_pdf_fixed_column-13.0.1.0.1.dev3.dist-info/top_level.txt
odoo13_addon_report_qweb_pdf_fixed_column-13.0.1.0.1.dev3.dist-info/RECORD
